brainsig/__init__.py
brainsig/dataset.py
brainsig/model.py
brainsig-0.1.0.dist-info/METADATA
brainsig-0.1.0.dist-info/WHEEL
brainsig-0.1.0.dist-info/licenses/LICENSE
brainsig-0.1.0.dist-info/RECORD
